{"uid":"197416","slug":"giorgos-georgiou","prenom":"Giorgos","nom":"GEORGIOU","civ":"","sexe":"H","dateNaissance":"1963-04-09","profession":null,"circo":{"departement":"🇨🇾 Cyprus","numDepartement":"CY","region":null,"numCirco":null},"countryCode":"CYP","flag":"🇨🇾","hatvp":null,"twitter":null,"facebook":null,"email":"giorgos.georgiou@europarl.europa.eu","website":null,"nPour":1971,"nContre":1834,"nAbstention":299,"nNonVotant":1178,"nPresent":4104,"nEligible":5282,"nLoyal":3756,"nGroupExpr":4104,"presenceRate":77.7,"participationRate":77.7,"nExprimes":4104,"loyaltyRate":91.5,"groupe":{"sigle":"The Left","libelle":"The Left in the European Parliament","color":"#8B0000"},"votesRecents":[{"numero":"194444","date":"2026-06-17","position":"pour","titre":"Common system for the return of third-country nationals staying illegally in the Union (Return Regulation)","sort":"rejeté"},{"numero":"194442","date":"2026-06-17","position":"pour","titre":"Common system for the return of third-country nationals staying illegally in the Union (Return Regulation)","sort":"rejeté"},{"numero":"194441","date":"2026-06-17","position":"pour","titre":"Plants obtained by certain new genomic techniques and their food and feed","sort":"rejeté"},{"numero":"194440","date":"2026-06-17","position":"pour","titre":"Plants obtained by certain new genomic techniques and their food and feed","sort":"rejeté"},{"numero":"194439","date":"2026-06-17","position":"pour","titre":"Plants obtained by certain new genomic techniques and their food and feed","sort":"rejeté"},{"numero":"194438","date":"2026-06-17","position":"pour","titre":"Plants obtained by certain new genomic techniques and their food and feed","sort":"rejeté"},{"numero":"194437","date":"2026-06-17","position":"pour","titre":"Plants obtained by certain new genomic techniques and their food and feed","sort":"rejeté"},{"numero":"194436","date":"2026-06-17","position":"pour","titre":"Plants obtained by certain new genomic techniques and their food and feed","sort":"rejeté"},{"numero":"194435","date":"2026-06-17","position":"pour","titre":"Plants obtained by certain new genomic techniques and their food and feed","sort":"rejeté"},{"numero":"194434","date":"2026-06-17","position":"pour","titre":"Plants obtained by certain new genomic techniques and their food and feed","sort":"rejeté"},{"numero":"194433","date":"2026-06-17","position":"pour","titre":"Plants obtained by certain new genomic techniques and their food and feed","sort":"rejeté"},{"numero":"194432","date":"2026-06-17","position":"pour","titre":"Plants obtained by certain new genomic techniques and their food and feed","sort":"rejeté"},{"numero":"194431","date":"2026-06-17","position":"pour","titre":"Plants obtained by certain new genomic techniques and their food and feed","sort":"rejeté"},{"numero":"194430","date":"2026-06-17","position":"pour","titre":"Plants obtained by certain new genomic techniques and their food and feed","sort":"rejeté"},{"numero":"194429","date":"2026-06-17","position":"pour","titre":"Plants obtained by certain new genomic techniques and their food and feed","sort":"rejeté"},{"numero":"194428","date":"2026-06-17","position":"pour","titre":"Plants obtained by certain new genomic techniques and their food and feed","sort":"rejeté"},{"numero":"194427","date":"2026-06-17","position":"pour","titre":"Plants obtained by certain new genomic techniques and their food and feed","sort":"rejeté"},{"numero":"194426","date":"2026-06-17","position":"pour","titre":"Plants obtained by certain new genomic techniques and their food and feed","sort":"rejeté"},{"numero":"194425","date":"2026-06-17","position":"pour","titre":"Plants obtained by certain new genomic techniques and their food and feed","sort":"rejeté"},{"numero":"194424","date":"2026-06-17","position":"pour","titre":"Plants obtained by certain new genomic techniques and their food and feed","sort":"rejeté"},{"numero":"194395","date":"2026-06-17","position":"pour","titre":"2025 Commission report on Albania","sort":"rejeté"},{"numero":"194394","date":"2026-06-17","position":"pour","titre":"2025 Commission report on Albania","sort":"rejeté"},{"numero":"194393","date":"2026-06-17","position":"pour","titre":"2025 Commission report on Albania","sort":"adopté"},{"numero":"194136","date":"2026-06-17","position":"abstention","titre":"Structure and rates of excise duty applied to tobacco and tobacco related products (recast)","sort":"rejeté"},{"numero":"194135","date":"2026-06-17","position":"abstention","titre":"Structure and rates of excise duty applied to tobacco and tobacco related products (recast)","sort":"adopté"}]}